setup.py
dsnd_probability_kt/Binomialdistribution.py
dsnd_probability_kt/Gaussiandistribution.py
dsnd_probability_kt/Generaldistribution.py
dsnd_probability_kt/__init__.py
dsnd_probability_kt.egg-info/PKG-INFO
dsnd_probability_kt.egg-info/SOURCES.txt
dsnd_probability_kt.egg-info/dependency_links.txt
dsnd_probability_kt.egg-info/not-zip-safe
dsnd_probability_kt.egg-info/top_level.txt