Metadata-Version: 1.0
Name: dsnd-probability-kt
Version: 0.1
Summary: Gaussian and Binomial distributions
Home-page: UNKNOWN
Author: Kayleigh Torok
Author-email: UNKNOWN
License: UNKNOWN
Platform: UNKNOWN
